Lugwit_Module
